<?xml version = '1.0' encoding = 'UTF-8'?>
<TriggerOraclev10g class="oracle.dbtools.crest.model.design.storage.oracle.v10g.TriggerOraclev10g" name="INSERT_TIME_SITE_034" directorySegmentName="seg_0" id="BA6DB436-37FB-0C13-BE51-2CACB86CE6EB">
<sourceConnName>osd11g</sourceConnName>
<sourceObjSchema>OSD</sourceObjSchema>
<sourceObjName>INSERT_TIME_SITE_034</sourceObjName>
<createdBy>Administrator</createdBy>
<createdTime>2014-12-02 09:16:55 UTC</createdTime>
<ownerDesignName>ACS1.2</ownerDesignName>
<actions>INSERT, UPDATE</actions>
<body>BEGIN&lt;br/&gt;IF DBMS_REPUTIL.FROM_REMOTE = FALSE THEN&lt;br/&gt;:NEW.TIME := SYSDATE;&lt;br/&gt;SELECT global_name INTO :NEW.SITE FROM GLOBAL_NAME;&lt;br/&gt;END IF;&lt;br/&gt;END;&lt;br/&gt;</body>
<triggerTime>BEFORE</triggerTime>
<owner>C5730B64-FB4D-9F2E-CCB9-0672373953FB</owner>
<table>569B1F7A-8127-B788-894D-7166B5A5093C</table>
</TriggerOraclev10g>