<?xml version = '1.0' encoding = 'UTF-8'?>
<Table class="oracle.dbtools.crest.model.design.relational.Table" directorySegmentName="seg_0" id="569B1F7A-8127-B788-894D-7166B5A5093C" name="RANGE">
<sourceConnName>osd11g</sourceConnName>
<sourceObjSchema>OSD</sourceObjSchema>
<sourceObjName>RANGE</sourceObjName>
<createdBy>Administrator</createdBy>
<createdTime>2014-12-02 09:16:50 UTC</createdTime>
<commentInRDBMS>???? ???? ????</commentInRDBMS>
<ownerDesignName>ACS1.2</ownerDesignName>
<remoteDesignID>FC08FCB9-B251-5E59-1CB2-BB8A37701BF3</remoteDesignID>
<remoteModelID>C4955F53-AD0F-2F13-12F5-4A3D5452E66A</remoteModelID>
<remoteObjectID>2FD8677D-0E6F-D7E3-64A4-608B8EF2F175</remoteObjectID>
<remoteObjectRelativeStorageName>\rel\C4955F53-4A3D5452E66A\table/seg_0/2FD8677D-0E6F-D7E3-64A4-608B8EF2F175.xml</remoteObjectRelativeStorageName>
<schemaObject>1894C33F-4036-073F-AD34-1CA4F5DC3AF8</schemaObject>
<allowColumnReorder>false</allowColumnReorder>
<existDependencyGenerateInDDl>true</existDependencyGenerateInDDl>
<columns itemClass="oracle.dbtools.crest.model.design.relational.Column">
<Column name="ORDER_RANGE" id="3278ED35-AB6F-E265-2968-C9592BD405C2">
<sourceConnName>osd11g</sourceConnName>
<sourceObjSchema>RANGE</sourceObjSchema>
<sourceObjName>ORDER_RANGE</sourceObjName>
<createdBy>Administrator</createdBy>
<createdTime>2014-12-02 09:16:52 UTC</createdTime>
<commentInRDBMS>?????</commentInRDBMS>
<ownerDesignName>ACS1.2</ownerDesignName>
<remoteObjectID>8777B0FF-01DC-D0DD-7698-2316C91B61D8</remoteObjectID>
<useDomainConstraints>false</useDomainConstraints>
<use>1</use>
<logicalDatatype>LOGDT019</logicalDatatype>
<dataTypePrecision>2</dataTypePrecision>
<autoIncrementCycle>false</autoIncrementCycle>
</Column>
<Column name="RANGE_NAME" id="E1B37D05-07F2-BB6A-BFAB-93DF193FA47C">
<sourceConnName>osd11g</sourceConnName>
<sourceObjSchema>RANGE</sourceObjSchema>
<sourceObjName>RANGE_NAME</sourceObjName>
<createdBy>Administrator</createdBy>
<createdTime>2014-12-02 09:16:52 UTC</createdTime>
<commentInRDBMS>?????</commentInRDBMS>
<ownerDesignName>ACS1.2</ownerDesignName>
<remoteObjectID>A44C28BB-6CFA-C9A1-0F42-D7CE97A64B70</remoteObjectID>
<nullsAllowed>true</nullsAllowed>
<useDomainConstraints>false</useDomainConstraints>
<use>1</use>
<logicalDatatype>LOGDT024</logicalDatatype>
<dataTypeSize>20 BYTE</dataTypeSize>
<autoIncrementCycle>false</autoIncrementCycle>
</Column>
<Column name="COUNT_DAYS" id="55285B27-4B84-7496-2E4D-9E49B2D26356">
<sourceConnName>osd11g</sourceConnName>
<sourceObjSchema>RANGE</sourceObjSchema>
<sourceObjName>COUNT_DAYS</sourceObjName>
<createdBy>Administrator</createdBy>
<createdTime>2014-12-02 09:16:52 UTC</createdTime>
<commentInRDBMS>??? ??????</commentInRDBMS>
<ownerDesignName>ACS1.2</ownerDesignName>
<remoteObjectID>52D2853C-F6C4-2D6F-BC6D-AE7401F7F9CD</remoteObjectID>
<nullsAllowed>true</nullsAllowed>
<useDomainConstraints>false</useDomainConstraints>
<use>1</use>
<logicalDatatype>LOGDT019</logicalDatatype>
<dataTypePrecision>3</dataTypePrecision>
<autoIncrementCycle>false</autoIncrementCycle>
</Column>
<Column name="TIME" id="7B81E84F-A8B4-80AD-F58F-34F2433B1835">
<sourceConnName>osd11g</sourceConnName>
<sourceObjSchema>RANGE</sourceObjSchema>
<sourceObjName>TIME</sourceObjName>
<createdBy>Administrator</createdBy>
<createdTime>2014-12-02 09:16:52 UTC</createdTime>
<ownerDesignName>ACS1.2</ownerDesignName>
<remoteObjectID>EF4F80D9-AFA9-AFC3-A8D5-6E0A5DDD4D93</remoteObjectID>
<nullsAllowed>true</nullsAllowed>
<useDomainConstraints>false</useDomainConstraints>
<use>1</use>
<logicalDatatype>LOGDT007</logicalDatatype>
<dataTypeSize>7</dataTypeSize>
<autoIncrementCycle>false</autoIncrementCycle>
</Column>
<Column name="SITE" id="3FEF2433-2F3C-0DC7-DFA0-5D8298683B6C">
<sourceConnName>osd11g</sourceConnName>
<sourceObjSchema>RANGE</sourceObjSchema>
<sourceObjName>SITE</sourceObjName>
<createdBy>Administrator</createdBy>
<createdTime>2014-12-02 09:16:52 UTC</createdTime>
<ownerDesignName>ACS1.2</ownerDesignName>
<remoteObjectID>333B1720-63AB-8C1B-6AA4-9644087E89DB</remoteObjectID>
<nullsAllowed>true</nullsAllowed>
<useDomainConstraints>false</useDomainConstraints>
<use>1</use>
<logicalDatatype>LOGDT024</logicalDatatype>
<dataTypeSize>30 BYTE</dataTypeSize>
<autoIncrementCycle>false</autoIncrementCycle>
</Column>
<Column name="Omrano" id="E2D0802C-EF41-6614-B269-B3FB61D8D534">
<createdBy>Administrator</createdBy>
<createdTime>2014-12-08 02:09:54 UTC</createdTime>
<ownerDesignName>ACS1.2</ownerDesignName>
<remoteObjectID>619D51B8-AE11-64F5-083E-9337EF15580E</remoteObjectID>
<nullsAllowed>true</nullsAllowed>
<useDomainConstraints>false</useDomainConstraints>
<use>1</use>
<autoIncrementCycle>false</autoIncrementCycle>
<nameFixed>true</nameFixed>
<propertyMap>
<property name="ctemplateID" value="693AEBE1-3B98-B809-3C63-8FF4ABF31CA3"/>
</propertyMap>
</Column>
<Column name="Column_2" id="BB211214-F8E6-AEAB-7979-A892F596093E">
<createdBy>Administrator</createdBy>
<createdTime>2014-12-08 02:09:54 UTC</createdTime>
<ownerDesignName>ACS1.2</ownerDesignName>
<remoteObjectID>EE0E66FC-2E8C-6E08-C4A9-FCD6C4490195</remoteObjectID>
<nullsAllowed>true</nullsAllowed>
<use>0</use>
<autoIncrementCycle>false</autoIncrementCycle>
<propertyMap>
<property name="ctemplateID" value="06AF3308-8DFE-88C1-8CC2-CF94563A2CB7"/>
</propertyMap>
</Column>
<Column name="Column_3" id="CCB739DC-3745-D94D-0460-E36C497D0988">
<createdBy>Administrator</createdBy>
<createdTime>2014-12-08 02:13:20 UTC</createdTime>
<ownerDesignName>ACS1.2</ownerDesignName>
<remoteObjectID>0EEE6678-45EE-E7EE-3182-9833AC7241C1</remoteObjectID>
<nullsAllowed>true</nullsAllowed>
<use>0</use>
<autoIncrementCycle>false</autoIncrementCycle>
<propertyMap>
<property name="ctemplateID" value="D83C7479-BFEE-12F2-3C64-0EA382346975"/>
</propertyMap>
</Column>
</columns>
<indexes itemClass="oracle.dbtools.crest.model.design.relational.Index">
<ind_PK_UK id="9EBA734C-877E-C69A-29E6-33AE2FF44820" name="PK_RANGE_ORDER">
<sourceConnName>osd11g</sourceConnName>
<sourceObjSchema>OSD</sourceObjSchema>
<sourceObjName>PK_RANGE_ORDER</sourceObjName>
<createdBy>Administrator</createdBy>
<createdTime>2014-12-02 09:16:55 UTC</createdTime>
<ownerDesignName>ACS1.2</ownerDesignName>
<remoteObjectID>A2A7BBCA-2B97-CFED-E5A7-2E35108F946E</remoteObjectID>
<pk>true</pk>
<indexState>Primary Constraint</indexState>
<isSurrogateKey>false</isSurrogateKey>
<indexColumnUsage>
<colUsage columnID="3278ED35-AB6F-E265-2968-C9592BD405C2"/>
</indexColumnUsage>
</ind_PK_UK>
<ind_PK_UK id="6B566E2F-9A62-FEB4-B54D-2158EB877FBD" name="PK_RANGE_ORDER">
<sourceConnName>osd11g</sourceConnName>
<sourceObjSchema>OSD</sourceObjSchema>
<sourceObjName>PK_RANGE_ORDER</sourceObjName>
<createdBy>Administrator</createdBy>
<createdTime>2014-12-02 09:16:53 UTC</createdTime>
<ownerDesignName>ACS1.2</ownerDesignName>
<remoteObjectID>E2B1B25F-D004-935F-F132-08E84871BC06</remoteObjectID>
<indexState>Unique Plain Index</indexState>
<schemaObject>1894C33F-4036-073F-AD34-1CA4F5DC3AF8</schemaObject>
<isSurrogateKey>false</isSurrogateKey>
<indexColumnUsage>
<colUsage columnID="3278ED35-AB6F-E265-2968-C9592BD405C2"/>
</indexColumnUsage>
</ind_PK_UK>
</indexes>
</Table>